lintai/__init__.py
lintai/cli.py
lintai/cli_support.py
lintai/adapters/__init__.py
lintai/adapters/bandit_dummy.py
lintai/components/autogen.py
lintai/components/crewai.py
lintai/components/dspy.py
lintai/components/langchain.py
lintai/core/__init__.py
lintai/core/finding.py
lintai/core/loader.py
lintai/core/report.py
lintai/detectors/__init__.py
lintai/detectors/base.py
lintai/detectors/insecure_eval.py
lintai/detectors/llm01_prompt_injection.py
lintai/detectors/llm02_insecure_output.py
lintai/detectors/llm02_secret_in_prompt.py
lintai/detectors/llm06_execessive_agency.py
lintai/detectors/llm_code_audit.py
lintai/detectors/pii_eval.py
lintai/dsl/__init__.py
lintai/dsl/loader.py
lintai/engine/__init__.py
lintai/engine/ai_tags.py
lintai/engine/analysis.py
lintai/engine/ast_utils.py
lintai/engine/classification.py
lintai/engine/component_types.py
lintai/engine/frameworks.py
lintai/engine/inventory_builder.py
lintai/engine/python_ast_unit.py
lintai/engine/visitor.py
lintai/llm/__init__.py
lintai/llm/anthropic.py
lintai/llm/azure.py
lintai/llm/base.py
lintai/llm/budget.py
lintai/llm/cohere.py
lintai/llm/dummy.py
lintai/llm/errors.py
lintai/llm/gemini.py
lintai/llm/openai.py
lintai/llm/token_util.py
lintai/models/inventory.py
lintai/ui/server.py
lintai/ui/frontend/dist/favicon.svg
lintai/ui/frontend/dist/index.html
lintai/ui/frontend/dist/mockServiceWorker.js
lintai/ui/frontend/dist/assets/CustomGraph-DBXxjBsQ.js
lintai/ui/frontend/dist/assets/CustomGraph-DBXxjBsQ.js.map
lintai/ui/frontend/dist/assets/index-BMmNBDvX.css
lintai/ui/frontend/dist/assets/index-Cy6U-KII.js
lintai/ui/frontend/dist/assets/index-Cy6U-KII.js.map
lintai/ui/frontend/node_modules/flatted/python/flatted.py
lintai-0.1.1.dist-info/licenses/LICENSE
lintai-0.1.1.dist-info/METADATA
lintai-0.1.1.dist-info/WHEEL
lintai-0.1.1.dist-info/entry_points.txt
lintai-0.1.1.dist-info/top_level.txt
lintai-0.1.1.dist-info/RECORD
