Metadata-Version: 2.4
Name: lintai
Version: 0.1.1
Summary: Shift-left LLM security analyzer
Author-email: Harsh Parandekar <harsh.parandekar@paskl.ai>
License: Apache-2.0
Classifier: Development Status :: 3 - Alpha
Classifier: Environment :: Console
Classifier: License :: OSI Approved :: Apache Software License
Classifier: Programming Language :: Python :: 3 :: Only
Classifier: Programming Language :: Python :: 3.10
Classifier: Topic :: Security
Requires-Python: >=3.10
License-File: LICENSE
Requires-Dist: typer>=0.12
Requires-Dist: importlib-metadata; python_version < "3.10"
Requires-Dist: pyyaml>=6.0
Requires-Dist: networkx>=3.2
Requires-Dist: python-dotenv>=1.0
Requires-Dist: pathspec
Requires-Dist: tiktoken
Requires-Dist: fastapi>=0.111
Requires-Dist: uvicorn[standard]>=0.29
Requires-Dist: python-multipart>=0.0.9
Provides-Extra: openai
Requires-Dist: openai<2.0,>=1.12; extra == "openai"
Provides-Extra: anthropic
Requires-Dist: anthropic<1.0,>=0.21; extra == "anthropic"
Provides-Extra: gemini
Requires-Dist: google-generativeai>=0.5; extra == "gemini"
Provides-Extra: cohere
Requires-Dist: cohere>=5.1; extra == "cohere"
Provides-Extra: all-llms
Requires-Dist: lintai[anthropic,cohere,gemini,openai]; extra == "all-llms"
Provides-Extra: ui
Requires-Dist: fastapi; extra == "ui"
Requires-Dist: uvicorn[standard]; extra == "ui"
Requires-Dist: python-multipart; extra == "ui"
Provides-Extra: dev
Requires-Dist: pytest; extra == "dev"
Requires-Dist: black; extra == "dev"
Requires-Dist: pre-commit; extra == "dev"
Dynamic: license-file
